shapeeditor/__init__.py
shapeeditor/__version__.py
shapeeditor/admin.py
shapeeditor/apps.py
shapeeditor/models.py
shapeeditor/tests.py
shapeeditor/urls.py
shapeeditor/views.py
shapeeditor/management/__init__.py
shapeeditor/management/commands/__init__.py
shapeeditor/management/commands/importhistory.py
shapeeditor/migrations/0001_initial.py
shapeeditor/migrations/__init__.py
shapeeditor/static/shapeeditor/.gitignore
shapeeditor/static/shapeeditor/8081832fc5cfbf634aa6.ttf
shapeeditor/static/shapeeditor/favicon.ico
shapeeditor/static/shapeeditor/css/main_style.css
shapeeditor/static/shapeeditor/css/main_style.css.map
shapeeditor/static/shapeeditor/js/main.bundle.js
shapeeditor/static/shapeeditor/js/main.bundle.js.LICENSE.txt
shapeeditor/static/shapeeditor/js/main.bundle.js.map
shapeeditor/static/shapeeditor/js/main_style.bundle.js
shapeeditor/static/shapeeditor/js/main_style.bundle.js.LICENSE.txt
shapeeditor/static/shapeeditor/js/main_style.bundle.js.map
shapeeditor/templates/shapeeditor/agency_section.html
shapeeditor/templates/shapeeditor/base.html
shapeeditor/templates/shapeeditor/calendar_section.html
shapeeditor/templates/shapeeditor/horizontal_tabs_menu.html
shapeeditor/templates/shapeeditor/index.html
shapeeditor/templates/shapeeditor/map_section.html
shapeeditor/templates/shapeeditor/routes_section.html
shapeeditor/templates/shapeeditor/scheme_section.html
shapeeditor/templates/shapeeditor/shapes_section.html
shapeeditor/templates/shapeeditor/stop_times_section.html
shapeeditor/templates/shapeeditor/stops_section.html
shapeeditor/templates/shapeeditor/top_bar.html
shapeeditor/templates/shapeeditor/trips_section.html
shapeeditor-0.1.14.dist-info/LICENSE
shapeeditor-0.1.14.dist-info/METADATA
shapeeditor-0.1.14.dist-info/WHEEL
shapeeditor-0.1.14.dist-info/top_level.txt
shapeeditor-0.1.14.dist-info/RECORD
