Metadata-Version: 2.1
Name: shapeeditor
Version: 0.1.14
Summary: GTFS Editor frontend app for Django
Home-page: https://github.com/jeancahu/GTFS_shapes_editor_JS
Author: Jeancarlo Hidalgo
Author-email: jeancahu@gmail.com
License: MIT
Platform: UNKNOWN
Classifier: License :: OSI Approved :: MIT License
Classifier: Programming Language :: Python
Classifier: Programming Language :: Python :: 3
Classifier: Programming Language :: Python :: 3.7
Classifier: Programming Language :: Python :: 3.8
Classifier: Programming Language :: Python :: 3.9
Classifier: Programming Language :: Python :: Implementation :: CPython
Classifier: Programming Language :: Python :: Implementation :: PyPy
Requires-Python: >=3.7.0
License-File: LICENSE
